napari_imc/__init__.py
napari_imc/_reader.py
napari_imc/_version.py
napari_imc/imc_controller.py
napari_imc/imc_widget.py
napari_imc/napari.yaml
napari_imc/io/__init__.py
napari_imc/io/base.py
napari_imc/io/imaxt.py
napari_imc/io/mcd.py
napari_imc/io/txt.py
napari_imc/models/__init__.py
napari_imc/models/base.py
napari_imc/models/channel.py
napari_imc/models/imc_file.py
napari_imc/models/imc_file_acquisition.py
napari_imc/models/imc_file_panorama.py
napari_imc/widgets/__init__.py
napari_imc/widgets/_color_picker.py
napari_imc/widgets/channel_controls_widget.py
napari_imc/widgets/channel_table_model.py
napari_imc/widgets/channel_table_view.py
napari_imc/widgets/imc_file_tree_model.py
napari_imc/widgets/imc_file_tree_view.py
napari_imc-0.6.5.dist-info/LICENSE
napari_imc-0.6.5.dist-info/METADATA
napari_imc-0.6.5.dist-info/WHEEL
napari_imc-0.6.5.dist-info/entry_points.txt
napari_imc-0.6.5.dist-info/top_level.txt
napari_imc-0.6.5.dist-info/RECORD
