Metadata-Version: 2.1
Name: napari-imc
Version: 0.6.5
Summary: Imaging Mass Cytometry (IMC) file type support for napari
Home-page: https://github.com/BodenmillerGroup/napari-imc
Author: Jonas Windhager
Author-email: jonas.windhager@uzh.ch
License: MIT
Project-URL: Bug Tracker, https://github.com/BodenmillerGroup/napari-imc/issues
Project-URL: Documentation, https://github.com/BodenmillerGroup/napari-imc#README.md
Project-URL: Source Code, https://github.com/BodenmillerGroup/napari-imc
Project-URL: User Support, https://github.com/BodenmillerGroup/napari-imc/issues
Classifier: Development Status :: 4 - Beta
Classifier: Intended Audience :: Science/Research
Classifier: Framework :: napari
Classifier: Topic :: Scientific/Engineering :: Bio-Informatics
Classifier: Topic :: Scientific/Engineering :: Image Processing
Classifier: Programming Language :: Python
Classifier: Programming Language :: Python :: 3
Classifier: Programming Language :: Python :: 3.8
Classifier: Programming Language :: Python :: 3.9
Classifier: Programming Language :: Python :: 3.10
Classifier: Operating System :: OS Independent
Classifier: License :: OSI Approved :: MIT License
Requires-Python: >=3.8
License-File: LICENSE
Requires-Dist: numpy
Requires-Dist: qtpy
Requires-Dist: readimc
Requires-Dist: superqt
